napari_power_widgets/__init__.py
napari_power_widgets/napari.yaml
napari_power_widgets/types.py
napari_power_widgets/_tests/__init__.py
napari_power_widgets/_tests/test_widgets.py
napari_power_widgets/_widgets/__init__.py
napari_power_widgets/_widgets/_buttoned.py
napari_power_widgets/_widgets/_camera.py
napari_power_widgets/_widgets/_coordinate.py
napari_power_widgets/_widgets/_features.py
napari_power_widgets/_widgets/_labels.py
napari_power_widgets/_widgets/_mouse.py
napari_power_widgets/_widgets/_multidim.py
napari_power_widgets/_widgets/_points.py
napari_power_widgets/_widgets/_shapes.py
napari_power_widgets/_widgets/_temp_shape.py
napari_power_widgets/_widgets/_typing.py
napari_power_widgets/_widgets/_utils.py
napari_power_widgets-0.0.1.dist-info/LICENSE
napari_power_widgets-0.0.1.dist-info/METADATA
napari_power_widgets-0.0.1.dist-info/WHEEL
napari_power_widgets-0.0.1.dist-info/entry_points.txt
napari_power_widgets-0.0.1.dist-info/top_level.txt
napari_power_widgets-0.0.1.dist-info/RECORD
