Metadata-Version: 2.1
Name: napari-power-widgets
Version: 0.0.1
Summary: Powerful widgets and type annotations for napari plugin widgets
Home-page: https://github.com/hanjinliu/napari-power-widgets
Author: Hanjin Liu
Author-email: liuhanjin-sc@g.ecc.u-tokyo.ac.jp
License: BSD-3-Clause
Project-URL: Bug Tracker, https://github.com/hanjinliu/napari-power-widgets/issues
Project-URL: Documentation, https://github.com/hanjinliu/napari-power-widgets#README.md
Project-URL: Source Code, https://github.com/hanjinliu/napari-power-widgets
Project-URL: User Support, https://github.com/hanjinliu/napari-power-widgets/issues
Classifier: Development Status :: 2 - Pre-Alpha
Classifier: Framework :: napari
Classifier: Intended Audience :: Developers
Classifier: License :: OSI Approved :: BSD License
Classifier: Operating System :: OS Independent
Classifier: Programming Language :: Python
Classifier: Programming Language :: Python :: 3
Classifier: Programming Language :: Python :: 3 :: Only
Classifier: Programming Language :: Python :: 3.8
Classifier: Programming Language :: Python :: 3.9
Classifier: Programming Language :: Python :: 3.10
Classifier: Topic :: Scientific/Engineering :: Image Processing
Requires-Python: >=3.8
License-File: LICENSE
Requires-Dist: numpy
Requires-Dist: pandas
Requires-Dist: typing-extensions
Requires-Dist: magicgui
Requires-Dist: napari
Provides-Extra: testing
Requires-Dist: tox ; extra == 'testing'
Requires-Dist: pytest ; extra == 'testing'
Requires-Dist: pytest-cov ; extra == 'testing'
Requires-Dist: pyqt5 ; extra == 'testing'
